rpsl_parser-0.1.3.dist-info/METADATA
rpsl_parser-0.1.3.dist-info/WHEEL
rpsl_parser-0.1.3.dist-info/license_files/LICENSE
rpsl_parser/__init__.py
rpsl_parser/rpsl_parser.cp312-win_amd64.pyd
rpsl_parser-0.1.3.dist-info/RECORD
