Metadata-Version: 2.1
Name: rpsl-parser
Version: 0.1.3
Classifier: Programming Language :: Rust
Classifier: Programming Language :: Python :: Implementation :: CPython
Classifier: Programming Language :: Python :: Implementation :: PyPy
Classifier: Intended Audience :: Information Technology
Classifier: Intended Audience :: System Administrators
Classifier: Intended Audience :: Telecommunications Industry
Classifier: Topic :: System :: Networking
Classifier: Topic :: Software Development :: Libraries :: Python Modules
Classifier: Typing :: Typed
License-File: LICENSE
Summary: An RFC 2622 conformant Routing Policy Specification Language (RPSL) parser with a focus on speed and correctness.
Keywords: rpsl,parser,routing,policy,whois
Home-Page: https://github.com/srv6d/rpsl-parser
Author: Marvin Vogt <m@rvinvogt.com>
Author-email: Marvin Vogt <m@rvinvogt.com>
License: MIT
Requires-Python: >=3.7
Project-URL: Repository, https://github.com/srv6d/rpsl-parser
Project-URL: Issues, https://github.com/srv6d/rpsl-parser/issues
